airiallm/__init__.py
airiallm/airiallm.py
airiallm/constants.py
airiallm/utils.py
airiallm-0.0.1.dist-info/LICENSE
airiallm-0.0.1.dist-info/METADATA
airiallm-0.0.1.dist-info/WHEEL
airiallm-0.0.1.dist-info/entry_points.txt
airiallm-0.0.1.dist-info/top_level.txt
airiallm-0.0.1.dist-info/RECORD
